Metadata-Version: 1.0
Name: micral
Version: 2.0
Summary: Analyse tool for microstructure
Home-page: UNKNOWN
Author: Yann LEROY
Author-email: yann.leroy102@orange.fr
License: MIT
Platform: UNKNOWN
